{
    "updated":  "2026-07-22 22:38",
    "days":  {
                 "2026-07-22":  {
                                    "visitors":  164,
                                    "newVisitors":  46,
                                    "views":  185,
                                    "sessions":  170,
                                    "clicks":  {

                                               },
                                    "src":  {
                                                "direct":  21,
                                                "insta":  111,
                                                "other":  53
                                            },
                                    "hours":  {
                                                  "19":  {
                                                             "clicks":  0,
                                                             "views":  10
                                                         },
                                                  "20":  {
                                                             "clicks":  0,
                                                             "views":  48
                                                         },
                                                  "21":  {
                                                             "clicks":  0,
                                                             "views":  51
                                                         },
                                                  "22":  {
                                                             "clicks":  0,
                                                             "views":  76
                                                         }
                                              },
                                    "dwellAvg":  1.9,
                                    "dwellMedian":  1,
                                    "dwellSamples":  50,
                                    "scrollAvg":  3.9,
                                    "backTotal":  6
                                }
             }
}
